h2ogpte/__init__.py
h2ogpte/connectors.py
h2ogpte/errors.py
h2ogpte/h2ogpte.py
h2ogpte/h2ogpte_async.py
h2ogpte/h2ogpte_sync_base.py
h2ogpte/session.py
h2ogpte/session_async.py
h2ogpte/shared_client.py
h2ogpte/types.py
h2ogpte/utils.py
h2ogpte/cli/__init__.py
h2ogpte/cli/main.py
h2ogpte/cli/commands/__init__.py
h2ogpte/cli/commands/dispatcher.py
h2ogpte/cli/commands/command_handlers/__init__.py
h2ogpte/cli/commands/command_handlers/agent.py
h2ogpte/cli/commands/command_handlers/chat.py
h2ogpte/cli/commands/command_handlers/clear.py
h2ogpte/cli/commands/command_handlers/collection.py
h2ogpte/cli/commands/command_handlers/config.py
h2ogpte/cli/commands/command_handlers/disconnect.py
h2ogpte/cli/commands/command_handlers/exit.py
h2ogpte/cli/commands/command_handlers/help.py
h2ogpte/cli/commands/command_handlers/history.py
h2ogpte/cli/commands/command_handlers/rag.py
h2ogpte/cli/commands/command_handlers/research_agent.py
h2ogpte/cli/commands/command_handlers/session.py
h2ogpte/cli/commands/command_handlers/status.py
h2ogpte/cli/core/__init__.py
h2ogpte/cli/core/app.py
h2ogpte/cli/core/config.py
h2ogpte/cli/core/encryption.py
h2ogpte/cli/core/session.py
h2ogpte/cli/integrations/__init__.py
h2ogpte/cli/integrations/agent.py
h2ogpte/cli/integrations/rag.py
h2ogpte/cli/ui/__init__.py
h2ogpte/cli/ui/hbot_prompt.py
h2ogpte/cli/ui/prompts.py
h2ogpte/cli/ui/status_bar.py
h2ogpte/cli/utils/__init__.py
h2ogpte/cli/utils/file_manager.py
h2ogpte/rest_async/__init__.py
h2ogpte/rest_async/api_client.py
h2ogpte/rest_async/api_response.py
h2ogpte/rest_async/configuration.py
h2ogpte/rest_async/exceptions.py
h2ogpte/rest_async/rest.py
h2ogpte/rest_async/api/__init__.py
h2ogpte/rest_async/api/agents_api.py
h2ogpte/rest_async/api/api_keys_api.py
h2ogpte/rest_async/api/chat_api.py
h2ogpte/rest_async/api/collections_api.py
h2ogpte/rest_async/api/configurations_api.py
h2ogpte/rest_async/api/document_ingestion_api.py
h2ogpte/rest_async/api/documents_api.py
h2ogpte-1.6.52.dist-info/METADATA
h2ogpte-1.6.52.dist-info/WHEEL
h2ogpte-1.6.52.dist-info/entry_points.txt
h2ogpte-1.6.52.dist-info/top_level.txt
h2ogpte-1.6.52.dist-info/RECORD
