Metadata-Version: 2.4
Name: h2ogpte
Version: 1.6.52
Summary: Client library for Enterprise h2oGPTe
Author-email: "H2O.ai, Inc." <support@h2o.ai>
Project-URL: Source, https://github.com/h2oai/h2ogpte
Project-URL: Issues, https://github.com/h2oai/h2ogpte/issues
Project-URL: Documentation, https://h2oai.github.io/h2ogpte/
Keywords: information-retrieval,LLM,large-language-models,question-answering,search,semantic-search,analytical-search,lexical-search,document-search,natural-language-querying
Classifier: Development Status :: 4 - Beta
Classifier: Programming Language :: Python
Classifier: Programming Language :: Python :: 3.8
Classifier: Programming Language :: Python :: 3.9
Classifier: Programming Language :: Python :: 3.10
Classifier: Programming Language :: Python :: 3.11
Classifier: Programming Language :: Python :: 3.12
Classifier: Programming Language :: Python :: Implementation :: CPython
Classifier: Programming Language :: Python :: Implementation :: PyPy
Requires-Python: >=3.8
Requires-Dist: aiofiles
Requires-Dist: aiohttp
Requires-Dist: aiohttp-retry
Requires-Dist: pydantic[dotenv]>=2.5.2
Requires-Dist: pydantic-settings>=2.0.3
Requires-Dist: requests
Requires-Dist: websockets==11.0.3
Requires-Dist: beautifulsoup4
Requires-Dist: bs4
Requires-Dist: lxml
Requires-Dist: pandas
Requires-Dist: httpx
Requires-Dist: h2o_authn
Requires-Dist: packaging
Requires-Dist: filetype
Requires-Dist: tzlocal
Requires-Dist: rich>=13.7.0
Requires-Dist: pathspec>=0.12.0
Requires-Dist: gitpython>=3.1.40
Requires-Dist: toml>=0.10.2
